{"id":"1654296667-6715-308949783","version":1,"type":"request","time":1654296667.593587,"method":"GET","url":"http:\/\/worth-the-weight.lan\/clockwork","uri":"\/clockwork","headers":{"Accept":["text\/html,application\/xhtml+xml,application\/xml;q=0.9,image\/avif,image\/webp,*\/*;q=0.8"],"Accept-Encoding":["gzip, deflate"],"Accept-Language":["en-US,en;q=0.5"],"Cache-Control":["no-cache"],"Connection":["keep-alive"],"Cookie":["PHPSESSID=f8b0b5655ca89ab7e10cfe75d339b525; remember_6TpGq1xR_F05q3tke-JkBw=pFldqmLLMx8Iym6Nb0AxnWxD%7EV__8V-vVaT-ucuRLWUY32Q3alvyNWvLN; XDEBUG_PROFILE=; clockwork-profile="],"Host":["worth-the-weight.lan"],"Pragma":["no-cache"],"Upgrade-Insecure-Requests":["1"],"User-Agent":["Mozilla\/5.0 (Macintosh; Intel Mac OS X 10.15; rv:100.0) Gecko\/20100101 Firefox\/100.0"]},"controller":null,"getData":[],"postData":[],"requestData":"","sessionData":{"_tracy":{"__type__":"array","redirect":{"__type__":"array"},"setup":{"__type__":"array"}},"auth_logged_in":true,"auth_user_id":3,"auth_email":"james@james.com","auth_username":"jamesjames","auth_status":0,"auth_roles":0,"auth_force_logout":5,"auth_remembered":false,"auth_last_resync":1654296118},"authenticatedUser":null,"cookies":{"PHPSESSID":"f8b0b5655ca89ab7e10cfe75d339b525","remember_6TpGq1xR_F05q3tke-JkBw":"pFldqmLLMx8Iym6Nb0AxnWxD~V__8V-vVaT-ucuRLWUY32Q3alvyNWvLN","XDEBUG_PROFILE":"","clockwork-profile":""},"responseTime":1654296667.674416,"responseStatus":200,"responseDuration":80.82914352416992,"memoryUsage":8388608,"middleware":[],"databaseQueries":[],"databaseQueriesCount":null,"databaseSlowQueries":null,"databaseSelects":null,"databaseInserts":null,"databaseUpdates":null,"databaseDeletes":null,"databaseOthers":null,"databaseDuration":0,"cacheQueries":[],"cacheReads":null,"cacheHits":null,"cacheWrites":null,"cacheDeletes":null,"cacheTime":null,"modelsActions":[],"modelsRetrieved":[],"modelsCreated":[],"modelsUpdated":[],"modelsDeleted":[],"redisCommands":[],"queueJobs":[],"timelineData":[],"log":[],"events":[],"routes":[],"notifications":[],"emailsData":[],"viewsData":[],"userData":[],"subrequests":[],"xdebug":[],"commandName":null,"commandArguments":[],"commandArgumentsDefaults":[],"commandOptions":[],"commandOptionsDefaults":[],"commandExitCode":null,"commandOutput":null,"jobName":null,"jobDescription":null,"jobStatus":null,"jobPayload":[],"jobQueue":null,"jobConnection":null,"jobOptions":[],"testName":null,"testStatus":null,"testStatusMessage":null,"testAsserts":[],"clientMetrics":[],"webVitals":[],"parent":null,"updateToken":"427f2a83"}